bosma_ble/__init__.py
bosma_ble/command.py
bosma_ble/lock.py
bosma_ble/model.py
bosma_ble/parsers.py
bosma_ble-0.1.0.dist-info/AUTHORS.rst
bosma_ble-0.1.0.dist-info/LICENSE
bosma_ble-0.1.0.dist-info/METADATA
bosma_ble-0.1.0.dist-info/WHEEL
bosma_ble-0.1.0.dist-info/top_level.txt
bosma_ble-0.1.0.dist-info/RECORD
