Metadata-Version: 2.1
Name: bosma-ble
Version: 0.1.0
Summary: Library for interacting with Bosma Smart Home (https://www.bosmasmarthome.com)
Home-page: https://github.com/brettjurgens/bosma
Author: Brett Jurgens
Author-email: brett@brettjurgens.com
License: MIT license
Keywords: bosma
Classifier: Development Status :: 2 - Pre-Alpha
Classifier: Intended Audience :: Developers
Classifier: License :: OSI Approved :: MIT License
Classifier: Natural Language :: English
Classifier: Programming Language :: Python :: 3
Classifier: Programming Language :: Python :: 3.6
Classifier: Programming Language :: Python :: 3.7
Classifier: Programming Language :: Python :: 3.8
Requires-Python: >=3.6
License-File: LICENSE
License-File: AUTHORS.rst
Requires-Dist: bleak >=0.21.1
Requires-Dist: bleak-retry-connector >=3.3.0
